{
  "data": {
    "items": [
      {
        "created": 1694623182026283000,
        "createdFormatted": "2023/09/13 18:39:42",
        "name": "رضوانشهر",
        "province": {
          "countryId": "ir",
          "created": 1694623180845037000,
          "name": "یزد",
          "uniqueId": "iran_yazd",
          "updated": 1694623180845037000,
          "userId": "",
          "visibility": "A",
          "workspaceId": ""
        },
        "provinceId": "iran_yazd",
        "uniqueId": "iran_city_1160",
        "updated": 1694623182026283000,
        "userId": "",
        "visibility": "A",
        "workspaceId": ""
      },
      {
        "created": 1694623182025133000,
        "createdFormatted": "2023/09/13 18:39:42",
        "name": "پیربازار",
        "province": {
          "countryId": "ir",
          "created": 1694623180839410000,
          "name": "گیلان",
          "uniqueId": "iran_gilan",
          "updated": 1694623180839410000,
          "userId": "",
          "visibility": "A",
          "workspaceId": ""
        },
        "provinceId": "iran_gilan",
        "uniqueId": "iran_city_1159",
        "updated": 1694623182025133000,
        "userId": "",
        "visibility": "A",
        "workspaceId": ""
      },
      {
        "created": 1694623182024214000,
        "createdFormatted": "2023/09/13 18:39:42",
        "name": "بینالود",
        "province": {
          "countryId": "ir",
          "created": 1694623180821916000,
          "name": "خراسان رضوی",
          "uniqueId": "iran_khorasan_razavi",
          "updated": 1694623180821916000,
          "userId": "",
          "visibility": "A",
          "workspaceId": ""
        },
        "provinceId": "iran_khorasan_razavi",
        "uniqueId": "iran_city_1155",
        "updated": 1694623182024214000,
        "userId": "",
        "visibility": "A",
        "workspaceId": ""
      },
      {
        "created": 1694623182023282000,
        "createdFormatted": "2023/09/13 18:39:42",
        "name": "قیامدشت",
        "province": {
          "countryId": "ir",
          "created": 1694623180818634000,
          "name": "تهران",
          "uniqueId": "iran_tehran",
          "updated": 1694623180818634000,
          "userId": "",
          "visibility": "A",
          "workspaceId": ""
        },
        "provinceId": "iran_tehran",
        "uniqueId": "iran_city_1153",
        "updated": 1694623182023282000,
        "userId": "",
        "visibility": "A",
        "workspaceId": ""
      },
      {
        "created": 1694623182022300000,
        "createdFormatted": "2023/09/13 18:39:42",
        "name": "گلبهار",
        "province": {
          "countryId": "ir",
          "created": 1694623180821916000,
          "name": "خراسان رضوی",
          "uniqueId": "iran_khorasan_razavi",
          "updated": 1694623180821916000,
          "userId": "",
          "visibility": "A",
          "workspaceId": ""
        },
        "provinceId": "iran_khorasan_razavi",
        "uniqueId": "iran_city_1150",
        "updated": 1694623182022300000,
        "userId": "",
        "visibility": "A",
        "workspaceId": ""
      },
      {
        "created": 1694623182021392000,
        "createdFormatted": "2023/09/13 18:39:42",
        "name": "تهران دشت",
        "province": {
          "countryId": "ir",
          "created": 1694623180815490000,
          "name": "البرز",
          "uniqueId": "iran_alborz",
          "updated": 1694623180815490000,
          "userId": "",
          "visibility": "A",
          "workspaceId": ""
        },
        "provinceId": "iran_alborz",
        "uniqueId": "iran_city_1138",
        "updated": 1694623182021392000,
        "userId": "",
        "visibility": "A",
        "workspaceId": ""
      },
      {
        "created": 1694623182020466000,
        "createdFormatted": "2023/09/13 18:39:42",
        "name": "ساوجبلاغ",
        "province": {
          "countryId": "ir",
          "created": 1694623180815490000,
          "name": "البرز",
          "uniqueId": "iran_alborz",
          "updated": 1694623180815490000,
          "userId": "",
          "visibility": "A",
          "workspaceId": ""
        },
        "provinceId": "iran_alborz",
        "uniqueId": "iran_city_1137",
        "updated": 1694623182020466000,
        "userId": "",
        "visibility": "A",
        "workspaceId": ""
      },
      {
        "created": 1694623182019503000,
        "createdFormatted": "2023/09/13 18:39:42",
        "name": "کردان",
        "province": {
          "countryId": "ir",
          "created": 1694623180815490000,
          "name": "البرز",
          "uniqueId": "iran_alborz",
          "updated": 1694623180815490000,
          "userId": "",
          "visibility": "A",
          "workspaceId": ""
        },
        "provinceId": "iran_alborz",
        "uniqueId": "iran_city_1135",
        "updated": 1694623182019503000,
        "userId": "",
        "visibility": "A",
        "workspaceId": ""
      },
      {
        "created": 1694623182018585000,
        "createdFormatted": "2023/09/13 18:39:42",
        "name": "زیباکنار",
        "province": {
          "countryId": "ir",
          "created": 1694623180839410000,
          "name": "گیلان",
          "uniqueId": "iran_gilan",
          "updated": 1694623180839410000,
          "userId": "",
          "visibility": "A",
          "workspaceId": ""
        },
        "provinceId": "iran_gilan",
        "uniqueId": "iran_city_1121",
        "updated": 1694623182018585000,
        "userId": "",
        "visibility": "A",
        "workspaceId": ""
      },
      {
        "created": 1694623182017588000,
        "createdFormatted": "2023/09/13 18:39:42",
        "name": "سادات شهر",
        "province": {
          "countryId": "ir",
          "created": 1694623180840404000,
          "name": "مازندران",
          "uniqueId": "iran_mazandaran",
          "updated": 1694623180840404000,
          "userId": "",
          "visibility": "A",
          "workspaceId": ""
        },
        "provinceId": "iran_mazandaran",
        "uniqueId": "iran_city_1119",
        "updated": 1694623182017588000,
        "userId": "",
        "visibility": "A",
        "workspaceId": ""
      },
      {
        "created": 1694623182016619000,
        "createdFormatted": "2023/09/13 18:39:42",
        "name": "مارلیک",
        "province": {
          "countryId": "ir",
          "created": 1694623180815490000,
          "name": "البرز",
          "uniqueId": "iran_alborz",
          "updated": 1694623180815490000,
          "userId": "",
          "visibility": "A",
          "workspaceId": ""
        },
        "provinceId": "iran_alborz",
        "uniqueId": "iran_city_1118",
        "updated": 1694623182016619000,
        "userId": "",
        "visibility": "A",
        "workspaceId": ""
      },
      {
        "created": 1694623182015650000,
        "createdFormatted": "2023/09/13 18:39:42",
        "name": "فردیس",
        "province": {
          "countryId": "ir",
          "created": 1694623180815490000,
          "name": "البرز",
          "uniqueId": "iran_alborz",
          "updated": 1694623180815490000,
          "userId": "",
          "visibility": "A",
          "workspaceId": ""
        },
        "provinceId": "iran_alborz",
        "uniqueId": "iran_city_1117",
        "updated": 1694623182015650000,
        "userId": "",
        "visibility": "A",
        "workspaceId": ""
      },
      {
        "created": 1694623182014366000,
        "createdFormatted": "2023/09/13 18:39:42",
        "name": "پرند",
        "province": {
          "countryId": "ir",
          "created": 1694623180818634000,
          "name": "تهران",
          "uniqueId": "iran_tehran",
          "updated": 1694623180818634000,
          "userId": "",
          "visibility": "A",
          "workspaceId": ""
        },
        "provinceId": "iran_tehran",
        "uniqueId": "iran_city_1116",
        "updated": 1694623182014366000,
        "userId": "",
        "visibility": "A",
        "workspaceId": ""
      },
      {
        "created": 1694623182012880000,
        "createdFormatted": "2023/09/13 18:39:42",
        "name": "یزد",
        "province": {
          "countryId": "ir",
          "created": 1694623180845037000,
          "name": "یزد",
          "uniqueId": "iran_yazd",
          "updated": 1694623180845037000,
          "userId": "",
          "visibility": "A",
          "workspaceId": ""
        },
        "provinceId": "iran_yazd",
        "uniqueId": "iran_city_1111",
        "updated": 1694623182012880000,
        "userId": "",
        "visibility": "A",
        "workspaceId": ""
      },
      {
        "created": 1694623182011936000,
        "createdFormatted": "2023/09/13 18:39:42",
        "name": "هرات",
        "province": {
          "countryId": "ir",
          "created": 1694623180845037000,
          "name": "یزد",
          "uniqueId": "iran_yazd",
          "updated": 1694623180845037000,
          "userId": "",
          "visibility": "A",
          "workspaceId": ""
        },
        "provinceId": "iran_yazd",
        "uniqueId": "iran_city_1110",
        "updated": 1694623182011936000,
        "userId": "",
        "visibility": "A",
        "workspaceId": ""
      },
      {
        "created": 1694623182010811000,
        "createdFormatted": "2023/09/13 18:39:42",
        "name": "نیر",
        "province": {
          "countryId": "ir",
          "created": 1694623180845037000,
          "name": "یزد",
          "uniqueId": "iran_yazd",
          "updated": 1694623180845037000,
          "userId": "",
          "visibility": "A",
          "workspaceId": ""
        },
        "provinceId": "iran_yazd",
        "uniqueId": "iran_city_1109",
        "updated": 1694623182010811000,
        "userId": "",
        "visibility": "A",
        "workspaceId": ""
      },
      {
        "created": 1694623182009905000,
        "createdFormatted": "2023/09/13 18:39:42",
        "name": "ندوشن",
        "province": {
          "countryId": "ir",
          "created": 1694623180845037000,
          "name": "یزد",
          "uniqueId": "iran_yazd",
          "updated": 1694623180845037000,
          "userId": "",
          "visibility": "A",
          "workspaceId": ""
        },
        "provinceId": "iran_yazd",
        "uniqueId": "iran_city_1108",
        "updated": 1694623182009905000,
        "userId": "",
        "visibility": "A",
        "workspaceId": ""
      },
      {
        "created": 1694623182008936000,
        "createdFormatted": "2023/09/13 18:39:42",
        "name": "میبد",
        "province": {
          "countryId": "ir",
          "created": 1694623180845037000,
          "name": "یزد",
          "uniqueId": "iran_yazd",
          "updated": 1694623180845037000,
          "userId": "",
          "visibility": "A",
          "workspaceId": ""
        },
        "provinceId": "iran_yazd",
        "uniqueId": "iran_city_1107",
        "updated": 1694623182008936000,
        "userId": "",
        "visibility": "A",
        "workspaceId": ""
      },
      {
        "created": 1694623182007963000,
        "createdFormatted": "2023/09/13 18:39:42",
        "name": "مهریز",
        "province": {
          "countryId": "ir",
          "created": 1694623180845037000,
          "name": "یزد",
          "uniqueId": "iran_yazd",
          "updated": 1694623180845037000,
          "userId": "",
          "visibility": "A",
          "workspaceId": ""
        },
        "provinceId": "iran_yazd",
        "uniqueId": "iran_city_1106",
        "updated": 1694623182007963000,
        "userId": "",
        "visibility": "A",
        "workspaceId": ""
      },
      {
        "created": 1694623182007023000,
        "createdFormatted": "2023/09/13 18:39:42",
        "name": "مهردشت",
        "province": {
          "countryId": "ir",
          "created": 1694623180845037000,
          "name": "یزد",
          "uniqueId": "iran_yazd",
          "updated": 1694623180845037000,
          "userId": "",
          "visibility": "A",
          "workspaceId": ""
        },
        "provinceId": "iran_yazd",
        "uniqueId": "iran_city_1105",
        "updated": 1694623182007023000,
        "userId": "",
        "visibility": "A",
        "workspaceId": ""
      },
      {
        "created": 1694623182006065000,
        "createdFormatted": "2023/09/13 18:39:42",
        "name": "مروست",
        "province": {
          "countryId": "ir",
          "created": 1694623180845037000,
          "name": "یزد",
          "uniqueId": "iran_yazd",
          "updated": 1694623180845037000,
          "userId": "",
          "visibility": "A",
          "workspaceId": ""
        },
        "provinceId": "iran_yazd",
        "uniqueId": "iran_city_1104",
        "updated": 1694623182006065000,
        "userId": "",
        "visibility": "A",
        "workspaceId": ""
      },
      {
        "created": 1694623182005165000,
        "createdFormatted": "2023/09/13 18:39:42",
        "name": "عقدا",
        "province": {
          "countryId": "ir",
          "created": 1694623180845037000,
          "name": "یزد",
          "uniqueId": "iran_yazd",
          "updated": 1694623180845037000,
          "userId": "",
          "visibility": "A",
          "workspaceId": ""
        },
        "provinceId": "iran_yazd",
        "uniqueId": "iran_city_1103",
        "updated": 1694623182005165000,
        "userId": "",
        "visibility": "A",
        "workspaceId": ""
      },
      {
        "created": 1694623182004296000,
        "createdFormatted": "2023/09/13 18:39:42",
        "name": "طبس",
        "province": {
          "countryId": "ir",
          "created": 1694623180845037000,
          "name": "یزد",
          "uniqueId": "iran_yazd",
          "updated": 1694623180845037000,
          "userId": "",
          "visibility": "A",
          "workspaceId": ""
        },
        "provinceId": "iran_yazd",
        "uniqueId": "iran_city_1101",
        "updated": 1694623182004296000,
        "userId": "",
        "visibility": "A",
        "workspaceId": ""
      },
      {
        "created": 1694623182003212000,
        "createdFormatted": "2023/09/13 18:39:42",
        "name": "شاهدیه",
        "province": {
          "countryId": "ir",
          "created": 1694623180845037000,
          "name": "یزد",
          "uniqueId": "iran_yazd",
          "updated": 1694623180845037000,
          "userId": "",
          "visibility": "A",
          "workspaceId": ""
        },
        "provinceId": "iran_yazd",
        "uniqueId": "iran_city_1100",
        "updated": 1694623182003212000,
        "userId": "",
        "visibility": "A",
        "workspaceId": ""
      },
      {
        "created": 1694623182002224000,
        "createdFormatted": "2023/09/13 18:39:42",
        "name": "زارچ",
        "province": {
          "countryId": "ir",
          "created": 1694623180845037000,
          "name": "یزد",
          "uniqueId": "iran_yazd",
          "updated": 1694623180845037000,
          "userId": "",
          "visibility": "A",
          "workspaceId": ""
        },
        "provinceId": "iran_yazd",
        "uniqueId": "iran_city_1099",
        "updated": 1694623182002224000,
        "userId": "",
        "visibility": "A",
        "workspaceId": ""
      },
      {
        "created": 1694623182001191000,
        "createdFormatted": "2023/09/13 18:39:42",
        "name": "دیهوک",
        "province": {
          "countryId": "ir",
          "created": 1694623180845037000,
          "name": "یزد",
          "uniqueId": "iran_yazd",
          "updated": 1694623180845037000,
          "userId": "",
          "visibility": "A",
          "workspaceId": ""
        },
        "provinceId": "iran_yazd",
        "uniqueId": "iran_city_1098",
        "updated": 1694623182001191000,
        "userId": "",
        "visibility": "A",
        "workspaceId": ""
      },
      {
        "created": 1694623182000178000,
        "createdFormatted": "2023/09/13 18:39:42",
        "name": "خضرآباد",
        "province": {
          "countryId": "ir",
          "created": 1694623180845037000,
          "name": "یزد",
          "uniqueId": "iran_yazd",
          "updated": 1694623180845037000,
          "userId": "",
          "visibility": "A",
          "workspaceId": ""
        },
        "provinceId": "iran_yazd",
        "uniqueId": "iran_city_1097",
        "updated": 1694623182000178000,
        "userId": "",
        "visibility": "A",
        "workspaceId": ""
      },
      {
        "created": 1694623181999118000,
        "createdFormatted": "2023/09/13 18:39:41",
        "name": "حمیدیا",
        "province": {
          "countryId": "ir",
          "created": 1694623180845037000,
          "name": "یزد",
          "uniqueId": "iran_yazd",
          "updated": 1694623180845037000,
          "userId": "",
          "visibility": "A",
          "workspaceId": ""
        },
        "provinceId": "iran_yazd",
        "uniqueId": "iran_city_1096",
        "updated": 1694623181999118000,
        "userId": "",
        "visibility": "A",
        "workspaceId": ""
      },
      {
        "created": 1694623181998184000,
        "createdFormatted": "2023/09/13 18:39:41",
        "name": "تفت",
        "province": {
          "countryId": "ir",
          "created": 1694623180845037000,
          "name": "یزد",
          "uniqueId": "iran_yazd",
          "updated": 1694623180845037000,
          "userId": "",
          "visibility": "A",
          "workspaceId": ""
        },
        "provinceId": "iran_yazd",
        "uniqueId": "iran_city_1095",
        "updated": 1694623181998184000,
        "userId": "",
        "visibility": "A",
        "workspaceId": ""
      },
      {
        "created": 1694623181997125000,
        "createdFormatted": "2023/09/13 18:39:41",
        "name": "بهاباد",
        "province": {
          "countryId": "ir",
          "created": 1694623180845037000,
          "name": "یزد",
          "uniqueId": "iran_yazd",
          "updated": 1694623180845037000,
          "userId": "",
          "visibility": "A",
          "workspaceId": ""
        },
        "provinceId": "iran_yazd",
        "uniqueId": "iran_city_1094",
        "updated": 1694623181997125000,
        "userId": "",
        "visibility": "A",
        "workspaceId": ""
      },
      {
        "created": 1694623181996087000,
        "createdFormatted": "2023/09/13 18:39:41",
        "name": "بفروئیه",
        "province": {
          "countryId": "ir",
          "created": 1694623180845037000,
          "name": "یزد",
          "uniqueId": "iran_yazd",
          "updated": 1694623180845037000,
          "userId": "",
          "visibility": "A",
          "workspaceId": ""
        },
        "provinceId": "iran_yazd",
        "uniqueId": "iran_city_1093",
        "updated": 1694623181996087000,
        "userId": "",
        "visibility": "A",
        "workspaceId": ""
      },
      {
        "created": 1694623181995171000,
        "createdFormatted": "2023/09/13 18:39:41",
        "name": "بافق",
        "province": {
          "countryId": "ir",
          "created": 1694623180845037000,
          "name": "یزد",
          "uniqueId": "iran_yazd",
          "updated": 1694623180845037000,
          "userId": "",
          "visibility": "A",
          "workspaceId": ""
        },
        "provinceId": "iran_yazd",
        "uniqueId": "iran_city_1092",
        "updated": 1694623181995171000,
        "userId": "",
        "visibility": "A",
        "workspaceId": ""
      },
      {
        "created": 1694623181994094000,
        "createdFormatted": "2023/09/13 18:39:41",
        "name": "اشکذر",
        "province": {
          "countryId": "ir",
          "created": 1694623180845037000,
          "name": "یزد",
          "uniqueId": "iran_yazd",
          "updated": 1694623180845037000,
          "userId": "",
          "visibility": "A",
          "workspaceId": ""
        },
        "provinceId": "iran_yazd",
        "uniqueId": "iran_city_1091",
        "updated": 1694623181994094000,
        "userId": "",
        "visibility": "A",
        "workspaceId": ""
      },
      {
        "created": 1694623181993175000,
        "createdFormatted": "2023/09/13 18:39:41",
        "name": "اردکان",
        "province": {
          "countryId": "ir",
          "created": 1694623180845037000,
          "name": "یزد",
          "uniqueId": "iran_yazd",
          "updated": 1694623180845037000,
          "userId": "",
          "visibility": "A",
          "workspaceId": ""
        },
        "provinceId": "iran_yazd",
        "uniqueId": "iran_city_1090",
        "updated": 1694623181993175000,
        "userId": "",
        "visibility": "A",
        "workspaceId": ""
      },
      {
        "created": 1694623181992256000,
        "createdFormatted": "2023/09/13 18:39:41",
        "name": "احمدآباد",
        "province": {
          "countryId": "ir",
          "created": 1694623180845037000,
          "name": "یزد",
          "uniqueId": "iran_yazd",
          "updated": 1694623180845037000,
          "userId": "",
          "visibility": "A",
          "workspaceId": ""
        },
        "provinceId": "iran_yazd",
        "uniqueId": "iran_city_1089",
        "updated": 1694623181992256000,
        "userId": "",
        "visibility": "A",
        "workspaceId": ""
      },
      {
        "created": 1694623181991350000,
        "createdFormatted": "2023/09/13 18:39:41",
        "name": "ابرکوه",
        "province": {
          "countryId": "ir",
          "created": 1694623180845037000,
          "name": "یزد",
          "uniqueId": "iran_yazd",
          "updated": 1694623180845037000,
          "userId": "",
          "visibility": "A",
          "workspaceId": ""
        },
        "provinceId": "iran_yazd",
        "uniqueId": "iran_city_1088",
        "updated": 1694623181991350000,
        "userId": "",
        "visibility": "A",
        "workspaceId": ""
      },
      {
        "created": 1694623181990365000,
        "createdFormatted": "2023/09/13 18:39:41",
        "name": "همدان",
        "province": {
          "countryId": "ir",
          "created": 1694623180843839000,
          "name": "همدان",
          "uniqueId": "iran_hamedan",
          "updated": 1694623180843839000,
          "userId": "",
          "visibility": "A",
          "workspaceId": ""
        },
        "provinceId": "iran_hamedan",
        "uniqueId": "iran_city_1087",
        "updated": 1694623181990365000,
        "userId": "",
        "visibility": "A",
        "workspaceId": ""
      },
      {
        "created": 1694623181989399000,
        "createdFormatted": "2023/09/13 18:39:41",
        "name": "نهاوند",
        "province": {
          "countryId": "ir",
          "created": 1694623180843839000,
          "name": "همدان",
          "uniqueId": "iran_hamedan",
          "updated": 1694623180843839000,
          "userId": "",
          "visibility": "A",
          "workspaceId": ""
        },
        "provinceId": "iran_hamedan",
        "uniqueId": "iran_city_1086",
        "updated": 1694623181989399000,
        "userId": "",
        "visibility": "A",
        "workspaceId": ""
      },
      {
        "created": 1694623181988448000,
        "createdFormatted": "2023/09/13 18:39:41",
        "name": "ملایر",
        "province": {
          "countryId": "ir",
          "created": 1694623180843839000,
          "name": "همدان",
          "uniqueId": "iran_hamedan",
          "updated": 1694623180843839000,
          "userId": "",
          "visibility": "A",
          "workspaceId": ""
        },
        "provinceId": "iran_hamedan",
        "uniqueId": "iran_city_1085",
        "updated": 1694623181988448000,
        "userId": "",
        "visibility": "A",
        "workspaceId": ""
      },
      {
        "created": 1694623181987514000,
        "createdFormatted": "2023/09/13 18:39:41",
        "name": "مریانج",
        "province": {
          "countryId": "ir",
          "created": 1694623180843839000,
          "name": "همدان",
          "uniqueId": "iran_hamedan",
          "updated": 1694623180843839000,
          "userId": "",
          "visibility": "A",
          "workspaceId": ""
        },
        "provinceId": "iran_hamedan",
        "uniqueId": "iran_city_1084",
        "updated": 1694623181987514000,
        "userId": "",
        "visibility": "A",
        "workspaceId": ""
      },
      {
        "created": 1694623181986409000,
        "createdFormatted": "2023/09/13 18:39:41",
        "name": "لالجین",
        "province": {
          "countryId": "ir",
          "created": 1694623180843839000,
          "name": "همدان",
          "uniqueId": "iran_hamedan",
          "updated": 1694623180843839000,
          "userId": "",
          "visibility": "A",
          "workspaceId": ""
        },
        "provinceId": "iran_hamedan",
        "uniqueId": "iran_city_1083",
        "updated": 1694623181986409000,
        "userId": "",
        "visibility": "A",
        "workspaceId": ""
      },
      {
        "created": 1694623181985339000,
        "createdFormatted": "2023/09/13 18:39:41",
        "name": "گیان",
        "province": {
          "countryId": "ir",
          "created": 1694623180843839000,
          "name": "همدان",
          "uniqueId": "iran_hamedan",
          "updated": 1694623180843839000,
          "userId": "",
          "visibility": "A",
          "workspaceId": ""
        },
        "provinceId": "iran_hamedan",
        "uniqueId": "iran_city_1082",
        "updated": 1694623181985339000,
        "userId": "",
        "visibility": "A",
        "workspaceId": ""
      },
      {
        "created": 1694623181984216000,
        "createdFormatted": "2023/09/13 18:39:41",
        "name": "گل تپه",
        "province": {
          "countryId": "ir",
          "created": 1694623180843839000,
          "name": "همدان",
          "uniqueId": "iran_hamedan",
          "updated": 1694623180843839000,
          "userId": "",
          "visibility": "A",
          "workspaceId": ""
        },
        "provinceId": "iran_hamedan",
        "uniqueId": "iran_city_1081",
        "updated": 1694623181984216000,
        "userId": "",
        "visibility": "A",
        "workspaceId": ""
      },
      {
        "created": 1694623181982900000,
        "createdFormatted": "2023/09/13 18:39:41",
        "name": "کبودر آهنگ",
        "province": {
          "countryId": "ir",
          "created": 1694623180843839000,
          "name": "همدان",
          "uniqueId": "iran_hamedan",
          "updated": 1694623180843839000,
          "userId": "",
          "visibility": "A",
          "workspaceId": ""
        },
        "provinceId": "iran_hamedan",
        "uniqueId": "iran_city_1080",
        "updated": 1694623181982900000,
        "userId": "",
        "visibility": "A",
        "workspaceId": ""
      },
      {
        "created": 1694623181981943000,
        "createdFormatted": "2023/09/13 18:39:41",
        "name": "قهاوند",
        "province": {
          "countryId": "ir",
          "created": 1694623180843839000,
          "name": "همدان",
          "uniqueId": "iran_hamedan",
          "updated": 1694623180843839000,
          "userId": "",
          "visibility": "A",
          "workspaceId": ""
        },
        "provinceId": "iran_hamedan",
        "uniqueId": "iran_city_1079",
        "updated": 1694623181981943000,
        "userId": "",
        "visibility": "A",
        "workspaceId": ""
      },
      {
        "created": 1694623181981017000,
        "createdFormatted": "2023/09/13 18:39:41",
        "name": "قروه درجزین",
        "province": {
          "countryId": "ir",
          "created": 1694623180843839000,
          "name": "همدان",
          "uniqueId": "iran_hamedan",
          "updated": 1694623180843839000,
          "userId": "",
          "visibility": "A",
          "workspaceId": ""
        },
        "provinceId": "iran_hamedan",
        "uniqueId": "iran_city_1078",
        "updated": 1694623181981017000,
        "userId": "",
        "visibility": "A",
        "workspaceId": ""
      },
      {
        "created": 1694623181980094000,
        "createdFormatted": "2023/09/13 18:39:41",
        "name": "فیروزان",
        "province": {
          "countryId": "ir",
          "created": 1694623180843839000,
          "name": "همدان",
          "uniqueId": "iran_hamedan",
          "updated": 1694623180843839000,
          "userId": "",
          "visibility": "A",
          "workspaceId": ""
        },
        "provinceId": "iran_hamedan",
        "uniqueId": "iran_city_1077",
        "updated": 1694623181980094000,
        "userId": "",
        "visibility": "A",
        "workspaceId": ""
      },
      {
        "created": 1694623181979148000,
        "createdFormatted": "2023/09/13 18:39:41",
        "name": "فرسفج",
        "province": {
          "countryId": "ir",
          "created": 1694623180843839000,
          "name": "همدان",
          "uniqueId": "iran_hamedan",
          "updated": 1694623180843839000,
          "userId": "",
          "visibility": "A",
          "workspaceId": ""
        },
        "provinceId": "iran_hamedan",
        "uniqueId": "iran_city_1076",
        "updated": 1694623181979148000,
        "userId": "",
        "visibility": "A",
        "workspaceId": ""
      },
      {
        "created": 1694623181978181000,
        "createdFormatted": "2023/09/13 18:39:41",
        "name": "فامنین",
        "province": {
          "countryId": "ir",
          "created": 1694623180843839000,
          "name": "همدان",
          "uniqueId": "iran_hamedan",
          "updated": 1694623180843839000,
          "userId": "",
          "visibility": "A",
          "workspaceId": ""
        },
        "provinceId": "iran_hamedan",
        "uniqueId": "iran_city_1075",
        "updated": 1694623181978181000,
        "userId": "",
        "visibility": "A",
        "workspaceId": ""
      },
      {
        "created": 1694623181977255000,
        "createdFormatted": "2023/09/13 18:39:41",
        "name": "صالح آباد",
        "province": {
          "countryId": "ir",
          "created": 1694623180843839000,
          "name": "همدان",
          "uniqueId": "iran_hamedan",
          "updated": 1694623180843839000,
          "userId": "",
          "visibility": "A",
          "workspaceId": ""
        },
        "provinceId": "iran_hamedan",
        "uniqueId": "iran_city_1074",
        "updated": 1694623181977255000,
        "userId": "",
        "visibility": "A",
        "workspaceId": ""
      }
    ],
    "itemsPerPage": 50,
    "startIndex": 0,
    "totalAvailableItems": 1119,
    "totalItems": 1119
  }
}