{
  "data": {
    "items": [
      {
        "created": 1694603490333123000,
        "createdFormatted": "2023/09/13 13:11:30",
        "description": "output and input mode",
        "index": 3,
        "uniqueId": "GPIO_MODE_INPUT_OUTPUT",
        "updated": 1694603490333123000,
        "userId": "",
        "visibility": "A",
        "workspaceId": ""
      },
      {
        "created": 1694603490329849000,
        "createdFormatted": "2023/09/13 13:11:30",
        "description": "output and input with open-drain mode",
        "index": 7,
        "uniqueId": "GPIO_MODE_INPUT_OUTPUT_OD",
        "updated": 1694603490329849000,
        "userId": "",
        "visibility": "A",
        "workspaceId": ""
      },
      {
        "created": 1694603490324501000,
        "createdFormatted": "2023/09/13 13:11:30",
        "description": "output only with open-drain mode",
        "index": 6,
        "uniqueId": "GPIO_MODE_OUTPUT_OD",
        "updated": 1694603490324501000,
        "userId": "",
        "visibility": "A",
        "workspaceId": ""
      },
      {
        "created": 1694603490320851000,
        "createdFormatted": "2023/09/13 13:11:30",
        "description": "output only mode",
        "index": 2,
        "uniqueId": "GPIO_MODE_OUTPUT",
        "updated": 1694603490320851000,
        "userId": "",
        "visibility": "A",
        "workspaceId": ""
      },
      {
        "created": 1694603490317110000,
        "createdFormatted": "2023/09/13 13:11:30",
        "description": "input only",
        "index": 1,
        "uniqueId": "GPIO_MODE_INPUT",
        "updated": 1694603490317110000,
        "userId": "",
        "visibility": "A",
        "workspaceId": ""
      },
      {
        "created": 1694603490312508000,
        "createdFormatted": "2023/09/13 13:11:30",
        "description": "disable input and output",
        "uniqueId": "GPIO_MODE_DISABLE",
        "updated": 1694603490312508000,
        "userId": "",
        "visibility": "A",
        "workspaceId": ""
      }
    ],
    "itemsPerPage": 9999,
    "startIndex": 0,
    "totalAvailableItems": 6,
    "totalItems": 6
  }
}